{"is_source_file": false, "format": "", "description": "", "external_files": [], "external_methods": [], "published": [], "classes": [], "methods": [], "calls": [], "search-terms": [], "state": 2, "file_id": 11, "knowledge_revision": 16, "git_revision": "7613eb89526813df4ec5ac2c0e7e87e21a2df084", "hash": "db48092a5da4eb7e19f7f3989c97b376", "format-version": 4, "code-base-name": "tic_tac_toe_frontend", "filename": "README.md", "revision_history": [{"16": "7613eb89526813df4ec5ac2c0e7e87e21a2df084"}]}